templatealchemy
templatealchemy_driver
