Metadata-Version: 1.1
Name: TemplateAlchemy
Version: 0.1.22
Summary: An un-opinionated template abstraction layer
Home-page: http://github.com/cadithealth/templatealchemy
Author: Philip J Grabner, Cadit Health Inc
Author-email: oss@cadit.com
License: MIT (http://opensource.org/licenses/MIT)
Keywords: template unopinionated abstraction layer sqlalchemy mako mustache
Platform: UNKNOWN
Classifier: Development Status :: 4 - Beta
Classifier: Intended Audience :: Developers
Classifier: Programming Language :: Python
Classifier: Operating System :: OS Independent
Classifier: Topic :: Software Development
Classifier: Natural Language :: English
Classifier: License :: OSI Approved :: MIT License
Classifier: License :: Public Domain
